randeli/__init__.py
randeli/cli.py
randeli/cmds/__init__.py
randeli/cmds/augment.py
randeli/cmds/bootstrap.py
randeli/cmds/config.py
randeli/cmds/inspect.py
randeli/cmds/map-fonts.py
randeli/cmds/handlers/__init__.py
randeli/cmds/handlers/augment/__init__.py
randeli/cmds/handlers/augment/epub.py
randeli/cmds/handlers/augment/pdf.py
randeli/librandeli/__init__.py
randeli/librandeli/notify.py
randeli/librandeli/trace.py
randeli/librandeli/backend/__init__.py
randeli/librandeli/backend/apryse.py
randeli/librandeli/backend/base.py
randeli/librandeli/backend/epub.py
randeli/policy/__init__.py
randeli/policy/actions.py
randeli/policy/rules.py
randeli-0.9.0.dist-info/LICENCE
randeli-0.9.0.dist-info/METADATA
randeli-0.9.0.dist-info/WHEEL
randeli-0.9.0.dist-info/entry_points.txt
randeli-0.9.0.dist-info/top_level.txt
randeli-0.9.0.dist-info/RECORD
