Metadata-Version: 2.1
Name: randeli
Version: 0.9.0
Summary: Augment EPUB & PDFs to aid reading by those who are neurodivergent (ADD/ADHD).
Author-email: Richard Offer <richard@whitequeen.com>
License: GPLv2
Project-URL: Repository, https://github.com/badonhill-io/randeli
Classifier: Programming Language :: Python :: 3
Requires-Python: <=3.12
License-File: LICENCE
Requires-Dist: requests
Requires-Dist: click
Requires-Dist: configobj
Requires-Dist: event-notifier
Requires-Dist: fonttools
Requires-Dist: pydantic
Requires-Dist: urllib3
Requires-Dist: bs4
Requires-Dist: lxml
Requires-Dist: loguru
